multirotor/__init__.py
multirotor/coords.py
multirotor/env.py
multirotor/helpers.py
multirotor/optimize.py
multirotor/physics.py
multirotor/simulation.py
multirotor/trajectories.py
multirotor/vehicle.py
multirotor/visualize.py
multirotor/controller/__init__.py
multirotor/controller/pid.py
multirotor/controller/scurves.py
multirotor/models/__init__.py
multirotor/models/djimavicpro.py
multirotor/models/tarott18.py
multirotor-0.5.0.dist-info/METADATA
multirotor-0.5.0.dist-info/WHEEL
multirotor-0.5.0.dist-info/top_level.txt
multirotor-0.5.0.dist-info/RECORD
