Metadata-Version: 2.1
Name: multirotor
Version: 0.5.0
Summary: Simulation testbed for multirotor vehicles.
Keywords: multirotor,simulation,gym,uav
Requires-Python: >=3.7
Requires-Dist: numpy
Requires-Dist: scipy
Requires-Dist: numba
Requires-Dist: matplotlib
Requires-Dist: gym
Requires-Dist: optuna
Provides-Extra: control
Requires-Dist: control ; extra == 'control'
Provides-Extra: dev
Requires-Dist: twine ; extra == 'dev'
Requires-Dist: build ; extra == 'dev'
Requires-Dist: jupyter ; extra == 'dev'
